scrapqd/__init__.py
scrapqd/__main__.py
scrapqd/app.py
scrapqd/client.py
scrapqd/factory_interface.py
scrapqd/_static/sample.html
scrapqd/common/__init__.py
scrapqd/common/helper.py
scrapqd/executor/__init__.py
scrapqd/executor/exception.py
scrapqd/executor/requests.py
scrapqd/executor/selenium.py
scrapqd/executor/selenium_driver/__init__.py
scrapqd/executor/selenium_driver/browsers.py
scrapqd/executor/selenium_driver/factory.py
scrapqd/executor/selenium_driver/selenium.py
scrapqd/fetch/__init__.py
scrapqd/fetch/exception.py
scrapqd/fetch/factory.py
scrapqd/fetch/interface.py
scrapqd/fetch/process.py
scrapqd/fetch/ua/__init__.py
scrapqd/gql/__init__.py
scrapqd/gql/cache.py
scrapqd/gql/constants.py
scrapqd/gql/document.py
scrapqd/gql/exception.py
scrapqd/gql/helper.py
scrapqd/gql/parser.py
scrapqd/gql/schema.py
scrapqd/gql/template.html
scrapqd/gql/enum/__init__.py
scrapqd/gql/enum/browser.py
scrapqd/gql/enum/data_type.py
scrapqd/gql/enum/executor.py
scrapqd/gql/leaves/__init__.py
scrapqd/gql/leaves/attr.py
scrapqd/gql/leaves/constant.py
scrapqd/gql/leaves/factory.py
scrapqd/gql/leaves/form.py
scrapqd/gql/leaves/link.py
scrapqd/gql/leaves/query_params.py
scrapqd/gql/leaves/regex.py
scrapqd/gql/leaves/text.py
scrapqd/gql/queries/__init__.py
scrapqd/gql/queries/common.py
scrapqd/gql/queries/factory.py
scrapqd/gql/queries/fetch.py
scrapqd/gql/queries/selenium.py
scrapqd/gql/scalar/__init__.py
scrapqd/gql/scalar/dictionary.py
scrapqd/gql/scalar/generic.py
scrapqd/gql_parser/__init__.py
scrapqd/gql_parser/data_type.py
scrapqd/gql_parser/exception.py
scrapqd/gql_parser/lxml_parser.py
scrapqd/settings/__init__.py
scrapqd/settings/_default_config.py
scrapqd/settings/_helper.py
scrapqd/settings/_loader.py
scrapqd/settings/_logging.py
scrapqd/settings/user_agents.dat
scrapqd-1.0.1b0.dist-info/LICENSE
scrapqd-1.0.1b0.dist-info/METADATA
scrapqd-1.0.1b0.dist-info/WHEEL
scrapqd-1.0.1b0.dist-info/top_level.txt
scrapqd-1.0.1b0.dist-info/RECORD
