Metadata-Version: 2.1
Name: scrapqd
Version: 1.0.1b0
Summary: Scrape query definition intends to eliminate backend process of crawling and focus on xpath needed to get data. Library queries are developed using graphql-core library.
Home-page: https://github.com/dduraipandian/scapqd
Author: Durai Pandian
Author-email: dduraipandian@gmail.com
License: UNKNOWN
Keywords: web scraping,selenium,harvester,harvest,spider,crawler,requests
Platform: UNKNOWN
Classifier: License :: OSI Approved :: MIT License
Classifier: Natural Language :: English
Classifier: Intended Audience :: Developers
Classifier: Operating System :: OS Independent
Classifier: Programming Language :: Python
Classifier: Programming Language :: Python :: 3
Classifier: Programming Language :: Python :: 3.7
Classifier: Programming Language :: Python :: 3.8
Classifier: Programming Language :: Python :: 3.9
Classifier: Programming Language :: Python :: Implementation :: CPython
Requires-Python: >=3.7
License-File: LICENSE
Requires-Dist: lxml (==4.8.0)
Requires-Dist: flask (==2.0.3)
Requires-Dist: graphql-server (==3.0.0b5)
Requires-Dist: requests (==2.27.1)
Requires-Dist: graphql-core (==3.2.0)
Requires-Dist: selenium (==4.1.3)
Requires-Dist: immutable-config (==1.0)
Requires-Dist: webdriver-manager (==3.5.3)
